setup.py
Calculator/__init__.py
MyCal1.egg-info/PKG-INFO
MyCal1.egg-info/SOURCES.txt
MyCal1.egg-info/dependency_links.txt
MyCal1.egg-info/top_level.txt